uniquebible/htmlResources/images/exlbl_large/BL1.png
uniquebible/htmlResources/images/exlbl_large/BL10.png
uniquebible/htmlResources/images/exlbl_large/BL100.png
uniquebible/htmlResources/images/exlbl_large/BL1000.png
uniquebible/htmlResources/images/exlbl_large/BL1001.png
uniquebible/htmlResources/images/exlbl_large/BL1002.png
uniquebible/htmlResources/images/exlbl_large/BL1003.png
uniquebible/htmlResources/images/exlbl_large/BL1004.png
uniquebible/htmlResources/images/exlbl_large/BL1006.png
uniquebible/htmlResources/images/exlbl_large/BL1007.png
uniquebible/htmlResources/images/exlbl_large/BL1008.png
uniquebible/htmlResources/images/exlbl_large/BL1009.png
uniquebible/htmlResources/images/exlbl_large/BL101.png
uniquebible/htmlResources/images/exlbl_large/BL1012.png
uniquebible/htmlResources/images/exlbl_large/BL1013.png
uniquebible/htmlResources/images/exlbl_large/BL1014.png
uniquebible/htmlResources/images/exlbl_large/BL1016.png
uniquebible/htmlResources/images/exlbl_large/BL1017.png
uniquebible/htmlResources/images/exlbl_large/BL1018.png
uniquebible/htmlResources/images/exlbl_large/BL1019.png
uniquebible/htmlResources/images/exlbl_large/BL102.png
uniquebible/htmlResources/images/exlbl_large/BL1020.png
uniquebible/htmlResources/images/exlbl_large/BL1021.png
uniquebible/htmlResources/images/exlbl_large/BL1022.png
uniquebible/htmlResources/images/exlbl_large/BL1023.png
uniquebible/htmlResources/images/exlbl_large/BL1024.png
uniquebible/htmlResources/images/exlbl_large/BL1025.png
uniquebible/htmlResources/images/exlbl_large/BL1026.png
uniquebible/htmlResources/images/exlbl_large/BL1027.png
uniquebible/htmlResources/images/exlbl_large/BL1028.png
uniquebible/htmlResources/images/exlbl_large/BL1029.png
uniquebible/htmlResources/images/exlbl_large/BL103.png
uniquebible/htmlResources/images/exlbl_large/BL1030.png
uniquebible/htmlResources/images/exlbl_large/BL1032.png
uniquebible/htmlResources/images/exlbl_large/BL1034.png
uniquebible_maps_2-0.0.3.dist-info/LICENSE
uniquebible_maps_2-0.0.3.dist-info/METADATA
uniquebible_maps_2-0.0.3.dist-info/WHEEL
uniquebible_maps_2-0.0.3.dist-info/top_level.txt
uniquebible_maps_2-0.0.3.dist-info/RECORD
